firebase/__init__.py
firebase/admin.py
firebase/apis.py
firebase/config.py
firebase/util.py
firebase_python-0.0.2.dist-info/METADATA
firebase_python-0.0.2.dist-info/WHEEL
firebase_python-0.0.2.dist-info/RECORD
